Workbook

Sheet Overview
A1: Chrona Test Case Suite
A2: Generated for Chrona QA planning on 2026-05-01. Scope includes Team, Clients, Projects, Tasks, Time Entry, Expenses, Approvals, Reports, and cross-cutting behavior.
A4: Suite Summary
A5: Total Test Cases | B5: =COUNTA('Test Cases'!A:A)-1 -> 211 | C5: Total User Stories | D5: =COUNTA(Traceability!A:A)-1 -> 95
A6: P0 Test Cases | B6: =COUNTIF('Test Cases'!J:J,"P0") -> 108 | C6: Automation Candidates | D6: =COUNTIF('Test Cases'!R:R,"Yes") -> 188
A7: P1 Test Cases | B7: =COUNTIF('Test Cases'!J:J,"P1") -> 95 | C7: Partial Automation | D7: =COUNTIF('Test Cases'!R:R,"Partial") -> 23
A8: P2 Test Cases | B8: =COUNTIF('Test Cases'!J:J,"P2") -> 8 | C8: Not Run | D8: =COUNTIF('Test Cases'!S:S,"Not Run") -> 211
A10: Module Coverage
A11: Module | B11: User Stories | C11: Test Cases | D11: P0 | E11: P1 | F11: P2 | G11: Automation Yes | H11: Execution Notes
A12: Team | B12: =COUNTIF(Traceability!B:B,A12) -> 21 | C12: =COUNTIF('Test Cases'!B:B,A12) -> 47 | D12: =COUNTIFS('Test Cases'!B:B,A12,'Test Cases'!J:J,"P0") -> 15 | E12: =COUNTIFS('Test Cases'!B:B,A12,'Test Cases'!J:J,"P1") -> 28 | F12: =COUNTIFS('Test Cases'!B:B,A12,'Test Cases'!J:J,"P2") -> 4 | G12: =COUNTIFS('Test Cases'!B:B,A12,'Test Cases'!R:R,"Yes") -> 45 | H12: Ready for QA execution; adjust owner and run status as releases are scheduled.
A13: Clients | B13: =COUNTIF(Traceability!B:B,A13) -> 11 | C13: =COUNTIF('Test Cases'!B:B,A13) -> 24 | D13: =COUNTIFS('Test Cases'!B:B,A13,'Test Cases'!J:J,"P0") -> 6 | E13: =COUNTIFS('Test Cases'!B:B,A13,'Test Cases'!J:J,"P1") -> 18 | F13: =COUNTIFS('Test Cases'!B:B,A13,'Test Cases'!J:J,"P2") -> 0 | G13: =COUNTIFS('Test Cases'!B:B,A13,'Test Cases'!R:R,"Yes") -> 24 | H13: Ready for QA execution; adjust owner and run status as releases are scheduled.
A14: Projects | B14: =COUNTIF(Traceability!B:B,A14) -> 18 | C14: =COUNTIF('Test Cases'!B:B,A14) -> 44 | D14: =COUNTIFS('Test Cases'!B:B,A14,'Test Cases'!J:J,"P0") -> 24 | E14: =COUNTIFS('Test Cases'!B:B,A14,'Test Cases'!J:J,"P1") -> 18 | F14: =COUNTIFS('Test Cases'!B:B,A14,'Test Cases'!J:J,"P2") -> 2 | G14: =COUNTIFS('Test Cases'!B:B,A14,'Test Cases'!R:R,"Yes") -> 44 | H14: Ready for QA execution; adjust owner and run status as releases are scheduled.
A15: Tasks | B15: =COUNTIF(Traceability!B:B,A15) -> 7 | C15: =COUNTIF('Test Cases'!B:B,A15) -> 13 | D15: =COUNTIFS('Test Cases'!B:B,A15,'Test Cases'!J:J,"P0") -> 2 | E15: =COUNTIFS('Test Cases'!B:B,A15,'Test Cases'!J:J,"P1") -> 11 | F15: =COUNTIFS('Test Cases'!B:B,A15,'Test Cases'!J:J,"P2") -> 0 | G15: =COUNTIFS('Test Cases'!B:B,A15,'Test Cases'!R:R,"Yes") -> 6 | H15: Ready for QA execution; adjust owner and run status as releases are scheduled.
A16: Time Entry | B16: =COUNTIF(Traceability!B:B,A16) -> 9 | C16: =COUNTIF('Test Cases'!B:B,A16) -> 16 | D16: =COUNTIFS('Test Cases'!B:B,A16,'Test Cases'!J:J,"P0") -> 16 | E16: =COUNTIFS('Test Cases'!B:B,A16,'Test Cases'!J:J,"P1") -> 0 | F16: =COUNTIFS('Test Cases'!B:B,A16,'Test Cases'!J:J,"P2") -> 0 | G16: =COUNTIFS('Test Cases'!B:B,A16,'Test Cases'!R:R,"Yes") -> 16 | H16: Ready for QA execution; adjust owner and run status as releases are scheduled.
A17: Expenses | B17: =COUNTIF(Traceability!B:B,A17) -> 8 | C17: =COUNTIF('Test Cases'!B:B,A17) -> 18 | D17: =COUNTIFS('Test Cases'!B:B,A17,'Test Cases'!J:J,"P0") -> 6 | E17: =COUNTIFS('Test Cases'!B:B,A17,'Test Cases'!J:J,"P1") -> 12 | F17: =COUNTIFS('Test Cases'!B:B,A17,'Test Cases'!J:J,"P2") -> 0 | G17: =COUNTIFS('Test Cases'!B:B,A17,'Test Cases'!R:R,"Yes") -> 18 | H17: Ready for QA execution; adjust owner and run status as releases are scheduled.
A18: Approvals | B18: =COUNTIF(Traceability!B:B,A18) -> 6 | C18: =COUNTIF('Test Cases'!B:B,A18) -> 17 | D18: =COUNTIFS('Test Cases'!B:B,A18,'Test Cases'!J:J,"P0") -> 17 | E18: =COUNTIFS('Test Cases'!B:B,A18,'Test Cases'!J:J,"P1") -> 0 | F18: =COUNTIFS('Test Cases'!B:B,A18,'Test Cases'!J:J,"P2") -> 0 | G18: =COUNTIFS('Test Cases'!B:B,A18,'Test Cases'!R:R,"Yes") -> 11 | H18: Ready for QA execution; adjust owner and run status as releases are scheduled.
A19: Reports | B19: =COUNTIF(Traceability!B:B,A19) -> 8 | C19: =COUNTIF('Test Cases'!B:B,A19) -> 23 | D19: =COUNTIFS('Test Cases'!B:B,A19,'Test Cases'!J:J,"P0") -> 21 | E19: =COUNTIFS('Test Cases'!B:B,A19,'Test Cases'!J:J,"P1") -> 0 | F19: =COUNTIFS('Test Cases'!B:B,A19,'Test Cases'!J:J,"P2") -> 2 | G19: =COUNTIFS('Test Cases'!B:B,A19,'Test Cases'!R:R,"Yes") -> 22 | H19: Ready for QA execution; adjust owner and run status as releases are scheduled.
A20: Cross-Cutting | B20: =COUNTIF(Traceability!B:B,A20) -> 7 | C20: =COUNTIF('Test Cases'!B:B,A20) -> 9 | D20: =COUNTIFS('Test Cases'!B:B,A20,'Test Cases'!J:J,"P0") -> 1 | E20: =COUNTIFS('Test Cases'!B:B,A20,'Test Cases'!J:J,"P1") -> 8 | F20: =COUNTIFS('Test Cases'!B:B,A20,'Test Cases'!J:J,"P2") -> 0 | G20: =COUNTIFS('Test Cases'!B:B,A20,'Test Cases'!R:R,"Yes") -> 2 | H20: Ready for QA execution; adjust owner and run status as releases are scheduled.
A23: Recommended Execution Strategy
A24: Phase | B24: Scope | C24: Recommended Focus
A25: Smoke | B25: P0 happy-path functional cases | C25: Verify major workflows: member setup, clients/projects, time and expenses, approval, reports.
A26: Sprint Regression | B26: All P0 and changed-module P1 cases | C26: Run after each feature increment and before stakeholder demos.
A27: Release Regression | B27: All P0/P1 plus selected P2 | C27: Include permission, locking, archive/delete restrictions, and financial calculations.
A28: Automation | B28: Validation, permission, API, calculation, and report consistency cases | C28: Prioritize deterministic cases marked Automation Candidate = Yes.

Sheet Test Cases
A1: Test Case ID | B1: Module | C1: Feature Area | D1: Related User Story ID | E1: Story Title | F1: Test Case Title | G1: Description | H1: Type | I1: Level | J1: Priority | K1: Persona / Role | L1: Preconditions | M1: Test Data | N1: Steps | O1: Expected Result | P1: Business Rule / Validation | Q1: Positive / Negative | R1: Automation Candidate | S1: Execution Status | T1: Owner | U1: Execution Date | V1: Actual Result | W1: Defect ID | X1: Notes | Y1: Requirement Source
A2: CHR-TC-0001 | B2: Team | C2: Members list | D2: CHR-US-001 | E2: View organization members | F2: Validate View organization members | G2: Ensure Chrona supports 'View organization members' for Administrator / Manager under the Team module. | H2: Functional | I2: UI | J2: P1 | K2: Administrator, Manager | L2: A Chrona organization exists. The tester has access to an Administrator account and at least one active member, manager, and invited user where applicable. | M2: Member: Alex Chen / alex.chen+tc@chrona.test; Role: Project Lead; Type: Employee; Timezone: America/New_York; Rates: 150 billable, 80 cost. | N2: 1. Log in as Administrator, Manager. 2. Navigate to Team > Members list. 3. Apply the default view or report date range. 4. Verify that the expected records, columns, filters, and row-level actions are visible. | O2: The 'View organization members' workflow completes successfully. Chrona shows a clear success state, persists the result, and updates related selectors, lists, reports, or approval queues as applicable. | P2: System behavior must match the mapped user story acceptance criteria and preserve auditability where sensitive changes are made. | Q2: Positive | R2: Yes | S2: Not Run | Y2: Chrona PRD / User Story Backlog
A3: CHR-TC-0002 | B3: Team | C3: Members list | D3: CHR-US-001 | E3: View organization members | F3: Verify permission enforcement for View organization members | G3: Ensure Chrona supports 'View organization members' for Administrator / Manager under the Team module. | H3: Permission | I3: Integration | J3: P1 | K3: Administrator, Manager | L3: A Chrona organization exists. The tester has access to an Administrator account and at least one active member, manager, and invited user where applicable. | M3: Member: Alex Chen / alex.chen+tc@chrona.test; Role: Project Lead; Type: Employee; Timezone: America/New_York; Rates: 150 billable, 80 cost. | N3: 1. Log in as a user without permission for 'View organization members'. 2. Navigate directly to the target URL and through the normal navigation path. 3. Attempt to view, create, edit, approve, delete, export, or configure data related to Members list. 4. Repeat as an authorized user. | O3: Unauthorized users cannot access or execute restricted actions. Controls are hidden or disabled in the UI, direct URL/API access is rejected, and authorized users can complete the action. | P3: System behavior must match the mapped user story acceptance criteria and preserve auditability where sensitive changes are made. | Q3: Negative | R3: Yes | S3: Not Run | Y3: Chrona PRD / User Story Backlog
A4: CHR-TC-0003 | B4: Team | C4: Member invitation | D4: CHR-US-002 | E4: Invite a new member | F4: Validate Invite a new member | G4: Ensure Chrona supports 'Invite a new member' for Administrator / Manager under the Team module. | H4: Functional | I4: UI | J4: P0 | K4: Administrator, Manager | L4: A Chrona organization exists. The tester has access to an Administrator account and at least one active member, manager, and invited user where applicable. | M4: Member: Alex Chen / alex.chen+tc@chrona.test; Role: Project Lead; Type: Employee; Timezone: America/New_York; Rates: 150 billable, 80 cost. | N4: 1. Log in as Administrator, Manager. 2. Navigate to Team > Member invitation. 3. Start the workflow for 'Invite a new member'. 4. Enter valid required data. 5. Save or confirm the action. 6. Refresh the page and verify the persisted result. | O4: The 'Invite a new member' workflow completes successfully. Chrona shows a clear success state, persists the result, and updates related selectors, lists, reports, or approval queues as applicable. | P4: System behavior must match the mapped user story acceptance criteria and preserve auditability where sensitive changes are made. | Q4: Positive | R4: Yes | S4: Not Run | Y4: Chrona PRD / User Story Backlog
A5: CHR-TC-0004 | B5: Team | C5: Member invitation | D5: CHR-US-002 | E5: Invite a new member | F5: Validate field and business-rule errors for Invite a new member | G5: Ensure Chrona supports 'Invite a new member' for Administrator / Manager under the Team module. | H5: Validation | I5: UI | J5: P0 | K5: Administrator, Manager | L5: A Chrona organization exists. The tester has access to an Administrator account and at least one active member, manager, and invited user where applicable. | M5: Member: Alex Chen / alex.chen+tc@chrona.test; Role: Project Lead; Type: Employee; Timezone: America/New_York; Rates: 150 billable, 80 cost. | N5: 1. Log in with a role that can access Team > Member invitation. 2. Start the 'Invite a new member' workflow. 3. Leave required fields blank or enter invalid/duplicate data where applicable. 4. Attempt to save or submit. 5. Correct the data and resubmit. | O5: Chrona blocks invalid submission, highlights each invalid field, preserves the user's entered data, shows actionable validation messages, and allows successful submission after corrections. | P5: System behavior must match the mapped user story acceptance criteria and preserve auditability where sensitive changes are made. | Q5: Negative | R5: Yes | S5: Not Run | Y5: Chrona PRD / User Story Backlog
A6: CHR-TC-0005 | B6: Team | C6: Member invitation | D6: CHR-US-002 | E6: Invite a new member | F6: Verify permission enforcement for Invite a new member | G6: Ensure Chrona supports 'Invite a new member' for Administrator / Manager under the Team module. | H6: Permission | I6: Integration | J6: P0 | K6: Administrator, Manager | L6: A Chrona organization exists. The tester has access to an Administrator account and at least one active member, manager, and invited user where applicable. | M6: Member: Alex Chen / alex.chen+tc@chrona.test; Role: Project Lead; Type: Employee; Timezone: America/New_York; Rates: 150 billable, 80 cost. | N6: 1. Log in as a user without permission for 'Invite a new member'. 2. Navigate directly to the target URL and through the normal navigation path. 3. Attempt to view, create, edit, approve, delete, export, or configure data related to Member invitation. 4. Repeat as an authorized user. | O6: Unauthorized users cannot access or execute restricted actions. Controls are hidden or disabled in the UI, direct URL/API access is rejected, and authorized users can complete the action. | P6: System behavior must match the mapped user story acceptance criteria and preserve auditability where sensitive changes are made. | Q6: Negative | R6: Yes | S6: Not Run | Y6: Chrona PRD / User Story Backlog
A7: CHR-TC-0006 | B7: Team | C7: Member invitation | D7: CHR-US-003 | E7: Prevent duplicate work emails | F7: Validate Prevent duplicate work emails | G7: Ensure Chrona supports 'Prevent duplicate work emails' for Administrator / Manager under the Team module. | H7: Functional | I7: UI | J7: P0 | K7: Administrator, Manager | L7: A Chrona organization exists. The tester has access to an Administrator account and at least one active member, manager, and invited user where applicable. | M7: Member: Alex Chen / alex.chen+tc@chrona.test; Role: Project Lead; Type: Employee; Timezone: America/New_York; Rates: 150 billable, 80 cost. | N7: 1. Log in as Administrator, Manager. 2. Navigate to Team > Member invitation. 3. Start the workflow for 'Prevent duplicate work emails'. 4. Enter valid required data. 5. Save or confirm the action. 6. Refresh the page and verify the persisted result. | O7: The 'Prevent duplicate work emails' workflow completes successfully. Chrona shows a clear success state, persists the result, and updates related selectors, lists, reports, or approval queues as applicable. | P7: Work email must be unique across active, invited, and archived members. | Q7: Positive | R7: Partial | S7: Not Run | Y7: Chrona PRD / User Story Backlog
A8: CHR-TC-0007 | B8: Team | C8: Member invitation | D8: CHR-US-003 | E8: Prevent duplicate work emails | F8: Verify permission enforcement for Prevent duplicate work emails | G8: Ensure Chrona supports 'Prevent duplicate work emails' for Administrator / Manager under the Team module. | H8: Permission | I8: Integration | J8: P0 | K8: Administrator, Manager | L8: A Chrona organization exists. The tester has access to an Administrator account and at least one active member, manager, and invited user where applicable. | M8: Member: Alex Chen / alex.chen+tc@chrona.test; Role: Project Lead; Type: Employee; Timezone: America/New_York; Rates: 150 billable, 80 cost. | N8: 1. Log in as a user without permission for 'Prevent duplicate work emails'. 2. Navigate directly to the target URL and through the normal navigation path. 3. Attempt to view, create, edit, approve, delete, export, or configure data related to Member invitation. 4. Repeat as an authorized user. | O8: Unauthorized users cannot access or execute restricted actions. Controls are hidden or disabled in the UI, direct URL/API access is rejected, and authorized users can complete the action. | P8: Work email must be unique across active, invited, and archived members. | Q8: Negative | R8: Yes | S8: Not Run | Y8: Chrona PRD / User Story Backlog
A9: CHR-TC-0008 | B9: Team | C9: Member invitation | D9: CHR-US-003 | E9: Prevent duplicate work emails | F9: Verify edge cases and historical integrity for Prevent duplicate work emails | G9: Ensure Chrona supports 'Prevent duplicate work emails' for Administrator / Manager under the Team module. | H9: Regression | I9: Integration | J9: P0 | K9: Administrator, Manager | L9: A Chrona organization exists. The tester has access to an Administrator account and at least one active member, manager, and invited user where applicable. | M9: Member: Alex Chen / alex.chen+tc@chrona.test; Role: Project Lead; Type: Employee; Timezone: America/New_York; Rates: 150 billable, 80 cost. | N9: 1. Prepare boundary data for Member invitation, including archived, referenced, historical, or date-effective records. 2. Execute the 'Prevent duplicate work emails' workflow. 3. Verify that Chrona handles the boundary condition without data corruption. 4. Verify audit history, reporting impact, and user-facing messages. | O9: Chrona enforces referential integrity, date-effective rules, archive/delete restrictions, and auditability. Existing historical data remains accurate and no orphaned records are created. | P9: Work email must be unique across active, invited, and archived members. | Q9: Edge | R9: Yes | S9: Not Run | Y9: Chrona PRD / User Story Backlog
A10: CHR-TC-0009 | B10: Team | C10: Member profile | D10: CHR-US-004 | E10: Edit member basic information | F10: Validate Edit member basic information | G10: Ensure Chrona supports 'Edit member basic information' for Administrator / Manager under the Team module. | H10: Functional | I10: UI | J10: P1 | K10: Administrator, Manager | L10: A Chrona organization exists. The tester has access to an Administrator account and at least one active member, manager, and invited user where applicable. | M10: Member: Alex Chen / alex.chen+tc@chrona.test; Role: Project Lead; Type: Employee; Timezone: America/New_York; Rates: 150 billable, 80 cost. | N10: 1. Log in as Administrator, Manager. 2. Navigate to Team > Member profile. 3. Start the workflow for 'Edit member basic information'. 4. Enter valid required data. 5. Save or confirm the action. 6. Refresh the page and verify the persisted result. | O10: The 'Edit member basic information' workflow completes successfully. Chrona shows a clear success state, persists the result, and updates related selectors, lists, reports, or approval queues as applicable. | P10: System behavior must match the mapped user story acceptance criteria and preserve auditability where sensitive changes are made. | Q10: Positive | R10: Yes | S10: Not Run | Y10: Chrona PRD / User Story Backlog
A11: CHR-TC-0010 | B11: Team | C11: Member profile | D11: CHR-US-004 | E11: Edit member basic information | F11: Verify permission enforcement for Edit member basic information | G11: Ensure Chrona supports 'Edit member basic information' for Administrator / Manager under the Team module. | H11: Permission | I11: Integration | J11: P1 | K11: Administrator, Manager | L11: A Chrona organization exists. The tester has access to an Administrator account and at least one active member, manager, and invited user where applicable. | M11: Member: Alex Chen / alex.chen+tc@chrona.test; Role: Project Lead; Type: Employee; Timezone: America/New_York; Rates: 150 billable, 80 cost. | N11: 1. Log in as a user without permission for 'Edit member basic information'. 2. Navigate directly to the target URL and through the normal navigation path. 3. Attempt to view, create, edit, approve, delete, export, or configure data related to Member profile. 4. Repeat as an authorized user. | O11: Unauthorized users cannot access or execute restricted actions. Controls are hidden or disabled in the UI, direct URL/API access is rejected, and authorized users can complete the action. | P11: System behavior must match the mapped user story acceptance criteria and preserve auditability where sensitive changes are made. | Q11: Negative | R11: Yes | S11: Not Run | Y11: Chrona PRD / User Story Backlog
A12: CHR-TC-0011 | B12: Team | C12: Member profile | D12: CHR-US-005 | E12: Manage member photo | F12: Validate Manage member photo | G12: Ensure Chrona supports 'Manage member photo' for Member / Administrator under the Team module. | H12: Functional | I12: UI | J12: P2 | K12: Member, Administrator | L12: A Chrona organization exists. The tester has access to an Administrator account and at least one active member, manager, and invited user where applicable. | M12: Member: Alex Chen / alex.chen+tc@chrona.test; Role: Project Lead; Type: Employee; Timezone: America/New_York; Rates: 150 billable, 80 cost. | N12: 1. Log in as Member, Administrator. 2. Navigate to Team > Member profile. 3. Perform the workflow for 'Manage member photo'. 4. Confirm that the UI, saved data, and downstream availability match the requirement. | O12: The 'Manage member photo' workflow completes successfully. Chrona shows a clear success state, persists the result, and updates related selectors, lists, reports, or approval queues as applicable. | P12: System behavior must match the mapped user story acceptance criteria and preserve auditability where sensitive changes are made. | Q12: Positive | R12: Partial | S12: Not Run | Y12: Chrona PRD / User Story Backlog
A13: CHR-TC-0012 | B13: Team | C13: Member profile | D13: CHR-US-005 | E13: Manage member photo | F13: Verify permission enforcement for Manage member photo | G13: Ensure Chrona supports 'Manage member photo' for Member / Administrator under the Team module. | H13: Permission | I13: Integration | J13: P2 | K13: Member, Administrator | L13: A Chrona organization exists. The tester has access to an Administrator account and at least one active member, manager, and invited user where applicable. | M13: Member: Alex Chen / alex.chen+tc@chrona.test; Role: Project Lead; Type: Employee; Timezone: America/New_York; Rates: 150 billable, 80 cost. | N13: 1. Log in as a user without permission for 'Manage member photo'. 2. Navigate directly to the target URL and through the normal navigation path. 3. Attempt to view, create, edit, approve, delete, export, or configure data related to Member profile. 4. Repeat as an authorized user. | O13: Unauthorized users cannot access or execute restricted actions. Controls are hidden or disabled in the UI, direct URL/API access is rejected, and authorized users can complete the action. | P13: System behavior must match the mapped user story acceptance criteria and preserve auditability where sensitive changes are made. | Q13: Negative | R13: Yes | S13: Not Run | Y13: Chrona PRD / User Story Backlog
... A212: CHR-TC-0211 | B212: Cross-Cutting | C212: Data integrity | D212: CHR-US-095 | E212: Protect referential integrity across modules | F212: Verify edge cases and historical integrity for Protect referential integrity across modules | G212: Ensure Chrona supports 'Protect referential integrity across modules' for System under the Cross-Cutting module. | H212: Data Integrity | I212: Integration | J212: P1 | K212: System | L212: A Chrona workspace exists with representative active, archived, and permission-restricted records. | M212: Use seeded workspace data that includes active, archived, permission-restricted, and historically referenced records. | N212: 1. Prepare boundary data for Data integrity, including archived, referenced, historical, or date-effective records. 2. Execute the 'Protect referential integrity across modules' workflow. 3. Verify that Chrona handles the boundary condition without data corruption. 4. Verify audit history, reporting impact, and user-facing messages. | O212: Chrona enforces referential integrity, date-effective rules, archive/delete restrictions, and auditability. Existing historical data remains accurate and no orphaned records are created. | P212: System behavior must match the mapped user story acceptance criteria and preserve auditability where sensitive changes are made. | Q212: Edge | R212: Yes | S212: Not Run | Y212: Chrona PRD / User Story Backlog

Sheet Traceability
A1: User Story ID | B1: Module | C1: Feature Area | D1: Persona / Role | E1: Story Title | F1: Priority | G1: Test Case Count | H1: Coverage Status | I1: Key Coverage Notes
A2: CHR-US-001 | B2: Team | C2: Members list | D2: Administrator, Manager | E2: View organization members | F2: P1 | G2: 2 | H2: Covered | I2: Covers happy path plus validation, permission, calculation, or edge scenarios based on story risk.
A3: CHR-US-002 | B3: Team | C3: Member invitation | D3: Administrator, Manager | E3: Invite a new member | F3: P0 | G3: 3 | H3: Covered | I3: Covers happy path plus validation, permission, calculation, or edge scenarios based on story risk.
A4: CHR-US-003 | B4: Team | C4: Member invitation | D4: Administrator, Manager | E4: Prevent duplicate work emails | F4: P0 | G4: 3 | H4: Covered | I4: Covers happy path plus validation, permission, calculation, or edge scenarios based on story risk.
A5: CHR-US-004 | B5: Team | C5: Member profile | D5: Administrator, Manager | E5: Edit member basic information | F5: P1 | G5: 2 | H5: Covered | I5: Covers happy path plus validation, permission, calculation, or edge scenarios based on story risk.
A6: CHR-US-005 | B6: Team | C6: Member profile | D6: Member, Administrator | E6: Manage member photo | F6: P2 | G6: 2 | H6: Covered | I6: Covers happy path plus validation, permission, calculation, or edge scenarios based on story risk.
A7: CHR-US-006 | B7: Team | C7: Member profile | D7: Administrator, Manager | E7: Configure timezone and notification preferences | F7: P1 | G7: 2 | H7: Covered | I7: Covers happy path plus validation, permission, calculation, or edge scenarios based on story risk.
A8: CHR-US-007 | B8: Team | C8: Member rates | D8: Administrator, Finance Manager | E8: Manage default billable and cost rates | F8: P0 | G8: 3 | H8: Covered | I8: Covers happy path plus validation, permission, calculation, or edge scenarios based on story risk.
A9: CHR-US-008 | B9: Team | C9: Member rates | D9: Administrator, Finance Manager | E9: View historical rate schedule | F9: P1 | G9: 2 | H9: Covered | I9: Covers happy path plus validation, permission, calculation, or edge scenarios based on story risk.
A10: CHR-US-009 | B10: Team | C10: Assigned projects | D10: Administrator, Manager | E10: Assign a member to projects | F10: P0 | G10: 3 | H10: Covered | I10: Covers happy path plus validation, permission, calculation, or edge scenarios based on story risk.
A11: CHR-US-010 | B11: Team | C11: Assigned projects | D11: Administrator, Manager | E11: Designate project management responsibility | F11: P1 | G11: 2 | H11: Covered | I11: Covers happy path plus validation, permission, calculation, or edge scenarios based on story risk.
A12: CHR-US-011 | B12: Team | C12: Assigned people | D12: Administrator, Manager | E12: Assign people to a manager | F12: P1 | G12: 2 | H12: Covered | I12: Covers happy path plus validation, permission, calculation, or edge scenarios based on story risk.
A13: CHR-US-012 | B13: Team | C13: Permissions | D13: Administrator | E13: Set system-level role | F13: P0 | G13: 3 | H13: Covered | I13: Covers happy path plus validation, permission, calculation, or edge scenarios based on story risk.
... A96: CHR-US-095 | B96: Cross-Cutting | C96: Data integrity | D96: System | E96: Protect referential integrity across modules | F96: P1 | G96: 2 | H96: Covered | I96: Covers happy path plus validation, permission, calculation, or edge scenarios based on story risk.

Sheet Test Data
A1: Data Set | B1: Field | C1: Sample Value | D1: Usage Notes
A2: Organization | B2: Workspace Name | C2: Chrona QA Workspace | D2: Use as the seeded organization for functional and regression testing.
A3: Organization | B3: Default Timezone | C3: America/New_York | D3: Used when a member-specific timezone is not configured.
A4: Member | B4: Administrator | C4: Morgan Admin / morgan.admin@chrona.test | D4: Has full Team, Clients, Projects, Tasks, Expense Categories, Reports, and Security access.
A5: Member | B5: Project Manager | C5: Priya Manager / priya.manager@chrona.test | D5: Manages Website Redesign and can approve submissions for assigned members.
A6: Member | B6: Team Member | C6: Alex Chen / alex.chen@chrona.test | D6: Can enter time and expenses on assigned projects.
A7: Member | B7: Restricted Member | C7: Noah Viewer / noah.viewer@chrona.test | D7: Used for permission-denied scenarios.
A8: Role | B8: Custom Role | C8: Project Lead | D8: Assignable to members from Team > Roles.
A9: Client | B9: Client Name | C9: Acme Design Co. | D9: Primary client used for project and reporting tests.
A10: Client | B10: Preferred Currency | C10: USD | D10: Also test EUR and JPY for localization/currency scenarios.
A11: Client | B11: Invoice Terms | C11: Custom 45 days | D11: Used for invoice due date configuration tests.
A12: Tax | B12: Primary Tax | C12: VAT 10% | D12: Used for client tax configuration.
... A27: Report Date Range | B27: Current Month | C27: First day to last day of current month | D27: Used for time, profitability, detailed time, and detailed expenses reports.

Sheet Field Guide
A1: Field | B1: Definition
A2: Test Case ID | B2: Unique identifier for the test case. Use this ID in QA management tools and defect reports.
A3: Module | B3: Primary product module under test.
A4: Feature Area | B4: Specific functional area within the module.
A5: Related User Story ID | B5: Traceability reference back to the Chrona user story backlog.
A6: Type | B6: Functional, Validation, Permission, Calculation, Regression, Data Integrity, or API-style coverage.
A7: Level | B7: UI, Integration, or System-level test.
A8: Priority | B8: P0 is release-blocking, P1 is required for normal release confidence, P2 is nice-to-have or lower risk.
A9: Persona / Role | B9: Role to use when executing the case.
A10: Preconditions | B10: System state required before execution begins.
A11: Test Data | B11: Recommended sample data for execution.
A12: Steps | B12: Ordered user or system actions.
... A16: Execution Status | B16: Default is Not Run. Replace with Passed, Failed, Blocked, or Not Applicable during execution.
